pattern_agentic_settings/__init__.py
pattern_agentic_settings/base.py
pattern_agentic_settings/hotreload.py
pattern_agentic_settings-2.0.0.dist-info/METADATA
pattern_agentic_settings-2.0.0.dist-info/WHEEL
pattern_agentic_settings-2.0.0.dist-info/licenses/LICENSE.md
pattern_agentic_settings-2.0.0.dist-info/licenses/LICENSE.md~
pattern_agentic_settings-2.0.0.dist-info/RECORD
