Metadata-Version: 2.4
Name: pattern_agentic_settings
Version: 2.0.0
Summary: Pydantic-powered config management
Author-email: Amos Joshua <amos@patternagentic.ai>
License-File: LICENSE.md
License-File: LICENSE.md~
Classifier: License :: OSI Approved :: MIT License
Classifier: Operating System :: OS Independent
Classifier: Programming Language :: Python :: 3
Requires-Python: >=3.11
Requires-Dist: pydantic-settings>=2.0.0
Requires-Dist: pydantic>=2.0.0
Provides-Extra: hotreload
Requires-Dist: watchfiles>=0.20.0; extra == 'hotreload'
